nnmerge/__init__.py
nnmerge/pytorch.py
nnmerge-0.1.2.dist-info/LICENSE
nnmerge-0.1.2.dist-info/METADATA
nnmerge-0.1.2.dist-info/WHEEL
nnmerge-0.1.2.dist-info/top_level.txt
nnmerge-0.1.2.dist-info/RECORD
