Metadata-Version: 2.1
Name: nnmerge
Version: 0.1.2
Summary: A library to merge multiple neural network models for parallel hyperparameter search
Home-page: https://github.com/wawancenggoro/nnmerge
Author: Wawan Cenggoro
Author-email: Wawan Cenggoro <wawancenggoro@gmail.com>
License: MIT
Project-URL: Homepage, https://github.com/wawancenggoro/nnmerge
Project-URL: Repository, https://github.com/wawancenggoro/nnmerge
Classifier: Development Status :: 1 - Planning
Classifier: Intended Audience :: Developers
Classifier: License :: OSI Approved :: MIT License
Classifier: Operating System :: OS Independent
Classifier: Programming Language :: Python :: 3
Classifier: Programming Language :: Python :: 3.7
Classifier: Programming Language :: Python :: 3.8
Classifier: Programming Language :: Python :: 3.9
Classifier: Programming Language :: Python :: 3.10
Classifier: Programming Language :: Python :: 3.11
Requires-Python: >=3.7
License-File: LICENSE
Requires-Dist: torch >=1.9.0
